Código/MapeamentoDisplay.v
module MapeamentoDisplay (
    input [4:0] entrada,
    input erropar,
    output reg [6:0] segmentos
);

always @(*) begin
    if (!erropar) begin
        segmentos = 7'b1011110; // Erro de Paridade
    end else begin
        case (entrada)
            5'd0: segmentos = 7'b1010100; // M
            5'd1: segmentos = 7'b0111011; // Y
            5'd2: segmentos = 7'b0011100; // V
            5'd3: segmentos = 7'b0110111; // H
            5'd4: segmentos = 7'b0001111; // T
            5'd5: segmentos = 7'b1111110; // 0
            5'd6: segmentos = 7'b1110111; // A
            5'd7: segmentos = 7'b1011011; // S
            5'd8: segmentos = 7'b1110011; // Q
            5'd9: segmentos = 7'b0101010; // W
            5'd10: segmentos = 7'b0001110; // L
            5'd11: segmentos = 7'b1111111; // 8
            5'd12: segmentos = 7'b0111101; // D
            5'd13: segmentos = 7'b1111001; // 3
            5'd14: segmentos = 7'b1101101; // 2
            5'd15: segmentos = 7'b1001111; // E
            5'd16: segmentos = 7'b0110111; // K
            5'd17: segmentos = 7'b0110011; // 4
            5'd18: segmentos = 7'b0000101; // R
            5'd19: segmentos = 7'b1111011; // 9
            default: segmentos = 7'b0000000; // Fora do intervalo
        endcase
    end
end

endmodule

Código/VerParidade.v
module VerParidade(
    input [5:0] X,
    output erropar
);

assign erropar = ( X[5] == ~(X[0] ^ X[1] ^ X[2] ^ X[3] ^ X[4])); // Calcula a paridade ímpar 

endmodule

Integracao.v
module Integracao (
    input [5:0] entrada,
    output [6:0] segmentos
);

wire erropar;

VerParidade verificador (
    .X(entrada),
    .erropar(erropar)
);

MapeamentoDisplay mapeador (
    .entrada(entrada[4:0]),
    .erropar(erropar),
    .segmentos(segmentos)
);

endmodule

Integracao_tb.v
`timescale 1ns / 1ps

module Integracao_tb;

reg [5:0] entrada;
wire [6:0] segmentos;

Integracao dut (
    .entrada(entrada),
    .segmentos(segmentos)
);

initial begin

    $dumpfile("Integracao_tb.vcd");
    $dumpvars(0, Integracao_tb);

    entrada = 6'd0; #5;
    entrada = 6'd1; #5;
    entrada = 6'd2; #5;
    entrada = 6'd3; #5;
    entrada = 6'd4; #5;
    entrada = 6'd5; #5;
    entrada = 6'd6; #5;
    entrada = 6'd7; #5;
    entrada = 6'd8; #5;
    entrada = 6'd9; #5;
    entrada = 6'd10; #5;
    entrada = 6'd11; #5;
    entrada = 6'd12; #5;
    entrada = 6'd13; #5;
    entrada = 6'd14; #5;
    entrada = 6'd15; #5;
    entrada = 6'd16; #5;
    entrada = 6'd17; #5;
    entrada = 6'd18; #5;
    entrada = 6'd19; #5;
    entrada = 6'd20; #5;
    entrada = 6'd21; #5;
    entrada = 6'd22; #5;
    entrada = 6'd23; #5;
    entrada = 6'd24; #5;
    entrada = 6'd25; #5;
    entrada = 6'd26; #5;
    entrada = 6'd27; #5;
    entrada = 6'd28; #5;
    entrada = 6'd29; #5;
    entrada = 6'd30; #5;
    entrada = 6'd31; #5;
    entrada = 6'd32; #5;
    entrada = 6'd33; #5;
    entrada = 6'd34; #5;
    entrada = 6'd35; #5;
    entrada = 6'd36; #5;
    entrada = 6'd37; #5;
    entrada = 6'd38; #5;
    entrada = 6'd39; #5;
    entrada = 6'd40; #5;
    entrada = 6'd41; #5;
    entrada = 6'd42; #5;
    entrada = 6'd43; #5;
    entrada = 6'd44; #5;
    entrada = 6'd45; #5;
    entrada = 6'd46; #5;
    entrada = 6'd47; #5;
    entrada = 6'd48; #5;
    entrada = 6'd49; #5;
    entrada = 6'd50; #5;
    entrada = 6'd51; #5;
    entrada = 6'd52; #5;
    entrada = 6'd53; #5;
    entrada = 6'd54; #5;
    entrada = 6'd55; #5;
    entrada = 6'd56; #5;
    entrada = 6'd57; #5;
    entrada = 6'd58; #5;
    entrada = 6'd59; #5;
    entrada = 6'd60; #5;
    entrada = 6'd61; #5;
    entrada = 6'd62; #5;
    entrada = 6'd63; #5;

    $finish;

end

endmodule

Código/Integracao_tb.vcd
$date
	Thu Nov 28 10:21:52 2024
$end
$version
	Icarus Verilog
$end
$timescale
	1ps
$end
$scope module Integracao_tb $end
$var wire 7 ! segmentos [6:0] $end
$var reg 6 " entrada [5:0] $end
$scope module dut $end
$var wire 6 # entrada [5:0] $end
$var wire 7 $ segmentos [6:0] $end
$var wire 1 % erropar $end
$scope module mapeador $end
$var wire 5 & entrada [4:0] $end
$var wire 1 % erropar $end
$var reg 7 ' segmentos [6:0] $end
$upscope $end
$scope module verificador $end
$var wire 6 ( X [5:0] $end
$var wire 1 % erropar $end
$upscope $end
$upscope $end
$upscope $end
$enddefinitions $end
$comment Show the parameter values. $end
$dumpall
$end
#0
$dumpvars
b0 (
b1011110 '
b0 &
0%
b1011110 $
b0 #
b0 "
b1011110 !
$end
#5000
b111011 !
b111011 $
b111011 '
1%
b1 &
b1 "
b1 #
b1 (
#10000
b11100 !
b11100 $
b11100 '
b10 &
b10 "
b10 #
b10 (
#15000
0%
b1011110 !
b1011110 $
b1011110 '
b11 &
b11 "
b11 #
b11 (
#20000
b1111 !
b1111 $
b1111 '
1%
b100 &
b100 "
b100 #
b100 (
#25000
0%
b1011110 !
b1011110 $
b1011110 '
b101 &
b101 "
b101 #
b101 (
#30000
b110 &
b110 "
b110 #
b110 (
#35000
b1011011 !
b1011011 $
b1011011 '
1%
b111 &
b111 "
b111 #
b111 (
#40000
1%
b1110011 !
b1110011 $
b1110011 '
b1000 &
b1000 "
b1000 #
b1000 (
#45000
0%
b1011110 !
b1011110 $
b1011110 '
b1001 &
b1001 "
b1001 #
b1001 (
#50000
b1010 &
b1010 "
b1010 #
b1010 (
#55000
b1111111 !
b1111111 $
b1111111 '
1%
b1011 &
b1011 "
b1011 #
b1011 (
#60000
0%
b1011110 !
b1011110 $
b1011110 '
b1100 &
b1100 "
b1100 #
b1100 (
#65000
b1111001 !
b1111001 $
b1111001 '
1%
b1101 &
b1101 "
b1101 #
b1101 (
#70000
b1101101 !
b1101101 $
b1101101 '
b1110 &
b1110 "
b1110 #
b1110 (
#75000
0%
b1011110 !
b1011110 $
b1011110 '
b1111 &
b1111 "
b1111 #
b1111 (
#80000
b110111 !
b110111 $
b110111 '
1%
b10000 &
b10000 "
b10000 #
b10000 (
#85000
0%
b1011110 !
b1011110 $
b1011110 '
b10001 &
b10001 "
b10001 #
b10001 (
#90000
b10010 &
b10010 "
b10010 #
b10010 (
#95000
b1111011 !
b1111011 $
b1111011 '
1%
b10011 &
b10011 "
b10011 #
b10011 (
#100000
0%
b1011110 !
b1011110 $
b1011110 '
b10100 &
b10100 "
b10100 #
b10100 (
#105000
b0 !
b0 $
b0 '
1%
b10101 &
b10101 "
b10101 #
b10101 (
#110000
b10110 &
b10110 "
b10110 #
b10110 (
#115000
b1011110 !
b1011110 $
b1011110 '
0%
b10111 &
b10111 "
b10111 #
b10111 (
#120000
b1011110 !
b1011110 $
b1011110 '
0%
b11000 &
b11000 "
b11000 #
b11000 (
#125000
b0 !
b0 $
b0 '
1%
b11001 &
b11001 "
b11001 #
b11001 (
#130000
b11010 &
b11010 "
b11010 #
b11010 (
#135000
b1011110 !
b1011110 $
b1011110 '
0%
b11011 &
b11011 "
b11011 #
b11011 (
#140000
b0 !
b0 $
b0 '
1%
b11100 &
b11100 "
b11100 #
b11100 (
#145000
b1011110 !
b1011110 $
b1011110 '
0%
b11101 &
b11101 "
b11101 #
b11101 (
#150000
b11110 &
b11110 "
b11110 #
b11110 (
#155000
b0 !
b0 $
b0 '
1%
b11111 &
b11111 "
b11111 #
b11111 (
#160000
b1010100 !
b1010100 $
b1010100 '
1%
b0 &
b100000 "
b100000 #
b100000 (
#165000
0%
b1011110 !
b1011110 $
b1011110 '
b1 &
b100001 "
b100001 #
b100001 (
#170000
b10 &
b100010 "
b100010 #
b100010 (
#175000
b110111 !
b110111 $
b110111 '
1%
b11 &
b100011 "
b100011 #
b100011 (
#180000
0%
b1011110 !
b1011110 $
b1011110 '
b100 &
b100100 "
b100100 #
b100100 (
#185000
b1111110 !
b1111110 $
b1111110 '
1%
b101 &
b100101 "
b100101 #
b100101 (
#190000
b1110111 !
b1110111 $
b1110111 '
b110 &
b100110 "
b100110 #
b100110 (
#195000
0%
b1011110 !
b1011110 $
b1011110 '
b111 &
b100111 "
b100111 #
b100111 (
#200000
b1011110 !
b1011110 $
b1011110 '
0%
b1000 &
b101000 "
b101000 #
b101000 (
#205000
b101010 !
b101010 $
b101010 '
1%
b1001 &
b101001 "
b101001 #
b101001 (
#210000
b1110 !
b1110 $
b1110 '
b1010 &
b101010 "
b101010 #
b101010 (
#215000
0%
b1011110 !
b1011110 $
b1011110 '
b1011 &
b101011 "
b101011 #
b101011 (
#220000
b111101 !
b111101 $
b111101 '
1%
b1100 &
b101100 "
b101100 #
b101100 (
#225000
0%
b1011110 !
b1011110 $
b1011110 '
b1101 &
b101101 "
b101101 #
b101101 (
#230000
b1110 &
b101110 "
b101110 #
b101110 (
#235000
b1001111 !
b1001111 $
b1001111 '
1%
b1111 &
b101111 "
b101111 #
b101111 (
#240000
0%
b1011110 !
b1011110 $
b1011110 '
b10000 &
b110000 "
b110000 #
b110000 (
#245000
b110011 !
b110011 $
b110011 '
1%
b10001 &
b110001 "
b110001 #
b110001 (
#250000
b101 !
b101 $
b101 '
b10010 &
b110010 "
b110010 #
b110010 (
#255000
0%
b1011110 !
b1011110 $
b1011110 '
b10011 &
b110011 "
b110011 #
b110011 (
#260000
b0 !
b0 $
b0 '
1%
b10100 &
b110100 "
b110100 #
b110100 (
#265000
b1011110 !
b1011110 $
b1011110 '
0%
b10101 &
b110101 "
b110101 #
b110101 (
#270000
b10110 &
b110110 "
b110110 #
b110110 (
#275000
b0 !
b0 $
b0 '
1%
b10111 &
b110111 "
b110111 #
b110111 (
#280000
b0 !
b0 $
b0 '
1%
b11000 &
b111000 "
b111000 #
b111000 (
#285000
b1011110 !
b1011110 $
b1011110 '
0%
b11001 &
b111001 "
b111001 #
b111001 (
#290000
b11010 &
b111010 "
b111010 #
b111010 (
#295000
b0 !
b0 $
b0 '
1%
b11011 &
b111011 "
b111011 #
b111011 (
#300000
b1011110 !
b1011110 $
b1011110 '
0%
b11100 &
b111100 "
b111100 #
b111100 (
#305000
b0 !
b0 $
b0 '
1%
b11101 &
b111101 "
b111101 #
b111101 (
#310000
b11110 &
b111110 "
b111110 #
b111110 (
#315000
b1011110 !
b1011110 $
b1011110 '
0%
b11111 &
b111111 "
b111111 #
b111111 (
